[
 {
  "ts": "2026-07-13T13:43:38+00:00",
  "ts_kst": "07-13 22:43",
  "kr_price": 1845000.0,
  "adr_price": 153.625,
  "usdkrw": 1492.78,
  "parity_usd": 123.59,
  "premium_pct": 24.3
 },
 {
  "ts": "2026-07-13T13:48:44+00:00",
  "ts_kst": "07-13 22:48",
  "kr_price": 1845000.0,
  "adr_price": 158.0,
  "usdkrw": 1493.3,
  "parity_usd": 123.55,
  "premium_pct": 27.88
 },
 {
  "ts": "2026-07-13T14:21:25+00:00",
  "ts_kst": "07-13 23:21",
  "kr_price": 1845000.0,
  "adr_price": 158.455,
  "usdkrw": 1494.56,
  "parity_usd": 123.45,
  "premium_pct": 28.36
 },
 {
  "ts": "2026-07-13T14:30:57+00:00",
  "ts_kst": "07-13 23:30",
  "kr_price": 1845000.0,
  "adr_price": 159.185,
  "usdkrw": 1493.48,
  "parity_usd": 123.54,
  "premium_pct": 28.86
 },
 {
  "ts": "2026-07-13T14:40:28+00:00",
  "ts_kst": "07-13 23:40",
  "kr_price": 1845000.0,
  "adr_price": 159.77,
  "usdkrw": 1495.28,
  "parity_usd": 123.39,
  "premium_pct": 29.49
 },
 {
  "ts": "2026-07-13T14:50:00+00:00",
  "ts_kst": "07-13 23:50",
  "kr_price": 1845000.0,
  "adr_price": 158.07,
  "usdkrw": 1493.38,
  "parity_usd": 123.55,
  "premium_pct": 27.95
 },
 {
  "ts": "2026-07-13T14:59:31+00:00",
  "ts_kst": "07-13 23:59",
  "kr_price": 1845000.0,
  "adr_price": 156.69,
  "usdkrw": 1493.38,
  "parity_usd": 123.55,
  "premium_pct": 26.83
 },
 {
  "ts": "2026-07-13T15:09:02+00:00",
  "ts_kst": "07-14 00:09",
  "kr_price": 1845000.0,
  "adr_price": 157.15,
  "usdkrw": 1493.2,
  "parity_usd": 123.56,
  "premium_pct": 27.19
 },
 {
  "ts": "2026-07-13T15:18:34+00:00",
  "ts_kst": "07-14 00:18",
  "kr_price": 1845000.0,
  "adr_price": 157.44,
  "usdkrw": 1493.48,
  "parity_usd": 123.54,
  "premium_pct": 27.44
 },
 {
  "ts": "2026-07-13T15:28:05+00:00",
  "ts_kst": "07-14 00:28",
  "kr_price": 1845000.0,
  "adr_price": 157.17,
  "usdkrw": 1493.78,
  "parity_usd": 123.51,
  "premium_pct": 27.25
 },
 {
  "ts": "2026-07-13T15:37:37+00:00",
  "ts_kst": "07-14 00:37",
  "kr_price": 1845000.0,
  "adr_price": 156.1,
  "usdkrw": 1493.25,
  "parity_usd": 123.56,
  "premium_pct": 26.34
 },
 {
  "ts": "2026-07-13T15:47:08+00:00",
  "ts_kst": "07-14 00:47",
  "kr_price": 1845000.0,
  "adr_price": 153.64,
  "usdkrw": 1492.99,
  "parity_usd": 123.58,
  "premium_pct": 24.33
 },
 {
  "ts": "2026-07-13T15:56:40+00:00",
  "ts_kst": "07-14 00:56",
  "kr_price": 1845000.0,
  "adr_price": 152.83,
  "usdkrw": 1491.78,
  "parity_usd": 123.68,
  "premium_pct": 23.57
 },
 {
  "ts": "2026-07-13T16:06:11+00:00",
  "ts_kst": "07-14 01:06",
  "kr_price": 1845000.0,
  "adr_price": 152.32,
  "usdkrw": 1492.33,
  "parity_usd": 123.63,
  "premium_pct": 23.2
 },
 {
  "ts": "2026-07-13T17:12:01+00:00",
  "ts_kst": "07-14 02:12",
  "kr_price": 1845000.0,
  "adr_price": 156.785,
  "usdkrw": 1496.27,
  "parity_usd": 123.31,
  "premium_pct": 27.15
 },
 {
  "ts": "2026-07-13T17:21:33+00:00",
  "ts_kst": "07-14 02:21",
  "kr_price": 1845000.0,
  "adr_price": 156.385,
  "usdkrw": 1495.87,
  "parity_usd": 123.34,
  "premium_pct": 26.79
 },
 {
  "ts": "2026-07-13T17:31:05+00:00",
  "ts_kst": "07-14 02:31",
  "kr_price": 1845000.0,
  "adr_price": 156.5,
  "usdkrw": 1495.95,
  "parity_usd": 123.33,
  "premium_pct": 26.89
 },
 {
  "ts": "2026-07-13T17:40:37+00:00",
  "ts_kst": "07-14 02:40",
  "kr_price": 1845000.0,
  "adr_price": 157.0,
  "usdkrw": 1497.23,
  "parity_usd": 123.23,
  "premium_pct": 27.41
 },
 {
  "ts": "2026-07-13T17:50:09+00:00",
  "ts_kst": "07-14 02:50",
  "kr_price": 1845000.0,
  "adr_price": 156.91,
  "usdkrw": 1497.06,
  "parity_usd": 123.24,
  "premium_pct": 27.32
 },
 {
  "ts": "2026-07-13T17:59:41+00:00",
  "ts_kst": "07-14 02:59",
  "kr_price": 1845000.0,
  "adr_price": 157.155,
  "usdkrw": 1497.06,
  "parity_usd": 123.24,
  "premium_pct": 27.52
 },
 {
  "ts": "2026-07-13T18:09:13+00:00",
  "ts_kst": "07-14 03:09",
  "kr_price": 1845000.0,
  "adr_price": 157.685,
  "usdkrw": 1496.3,
  "parity_usd": 123.3,
  "premium_pct": 27.88
 },
 {
  "ts": "2026-07-13T18:18:45+00:00",
  "ts_kst": "07-14 03:18",
  "kr_price": 1845000.0,
  "adr_price": 157.044,
  "usdkrw": 1496.38,
  "parity_usd": 123.3,
  "premium_pct": 27.37
 },
 {
  "ts": "2026-07-13T18:28:16+00:00",
  "ts_kst": "07-14 03:28",
  "kr_price": 1845000.0,
  "adr_price": 156.715,
  "usdkrw": 1496.19,
  "parity_usd": 123.31,
  "premium_pct": 27.09
 },
 {
  "ts": "2026-07-13T18:37:48+00:00",
  "ts_kst": "07-14 03:37",
  "kr_price": 1845000.0,
  "adr_price": 155.08,
  "usdkrw": 1496.72,
  "parity_usd": 123.27,
  "premium_pct": 25.81
 },
 {
  "ts": "2026-07-13T18:47:20+00:00",
  "ts_kst": "07-14 03:47",
  "kr_price": 1845000.0,
  "adr_price": 154.345,
  "usdkrw": 1497.26,
  "parity_usd": 123.23,
  "premium_pct": 25.25
 },
 {
  "ts": "2026-07-13T18:56:52+00:00",
  "ts_kst": "07-14 03:56",
  "kr_price": 1845000.0,
  "adr_price": 153.505,
  "usdkrw": 1496.8,
  "parity_usd": 123.26,
  "premium_pct": 24.53
 },
 {
  "ts": "2026-07-13T19:21:42+00:00",
  "ts_kst": "07-14 04:21",
  "kr_price": 1845000.0,
  "adr_price": 153.0,
  "usdkrw": 1496.72,
  "parity_usd": 123.27,
  "premium_pct": 24.12
 },
 {
  "ts": "2026-07-13T19:31:14+00:00",
  "ts_kst": "07-14 04:31",
  "kr_price": 1845000.0,
  "adr_price": 152.61,
  "usdkrw": 1496.69,
  "parity_usd": 123.27,
  "premium_pct": 23.8
 },
 {
  "ts": "2026-07-13T19:40:46+00:00",
  "ts_kst": "07-14 04:40",
  "kr_price": 1845000.0,
  "adr_price": 152.365,
  "usdkrw": 1497.4,
  "parity_usd": 123.21,
  "premium_pct": 23.66
 },
 {
  "ts": "2026-07-13T19:50:17+00:00",
  "ts_kst": "07-14 04:50",
  "kr_price": 1845000.0,
  "adr_price": 152.905,
  "usdkrw": 1497.68,
  "parity_usd": 123.19,
  "premium_pct": 24.12
 },
 {
  "ts": "2026-07-13T19:59:48+00:00",
  "ts_kst": "07-14 04:59",
  "kr_price": 1845000.0,
  "adr_price": 153.14,
  "usdkrw": 1497.59,
  "parity_usd": 123.2,
  "premium_pct": 24.3
 },
 {
  "ts": "2026-07-13T20:09:19+00:00",
  "ts_kst": "07-14 05:09",
  "kr_price": 1845000.0,
  "adr_price": 152.35,
  "usdkrw": 1497.59,
  "parity_usd": 123.2,
  "premium_pct": 23.66
 },
 {
  "ts": "2026-07-13T20:18:50+00:00",
  "ts_kst": "07-14 05:18",
  "kr_price": 1845000.0,
  "adr_price": 152.35,
  "usdkrw": 1497.57,
  "parity_usd": 123.2,
  "premium_pct": 23.66
 }
]